grai_graph/__init__.py
grai_graph/analysis.py
grai_graph/client_monkeypatch.py
grai_graph/graph.py
grai_graph/utils.py
grai_graph/visualizations.py
grai_graph-0.2.5.dist-info/METADATA
grai_graph-0.2.5.dist-info/WHEEL
grai_graph-0.2.5.dist-info/RECORD
